Workbook

Sheet MOVIMIENTOS
A1: Fecha | B1: Tipo | C1: Proyecto | D1: Categoria | E1: Descripcion | F1: Valor | G1: Metodo_Pago | H1: Observaciones

Sheet DASHBOARD
A1: SISTEMA FINANCIERO AMBIENTAL
A5: Dinero Total | B5: 2128000 | D5: Entradas Totales | E5: =SUMIF(MOVIMIENTOS!B:B,"Entrada",MOVIMIENTOS!F:F) -> 0
A6: Operación | B6: 851200 | D6: Gastos Totales | E6: =SUMIF(MOVIMIENTOS!B:B,"Gasto",MOVIMIENTOS!F:F) -> 0
A7: Personal | B7: 638400 | D7: Balance General | E7: =E5-E6 -> 0
A8: Ahorro | B8: 425600 | D8: Dinero Disponible | E8: =2128000+E7 -> 0
A9: Yogurt | B9: 212800

Sheet PROYECTOS
A1: CONTROL DE PROYECTOS
A4: Proyecto | B4: Ingresos | C4: Gastos | D4: Utilidad | E4: Margen | F4: % Operativo
A5: Corponor | B5: =SUMIFS(MOVIMIENTOS!F:F,MOVIMIENTOS!C:C,"Corponor",MOVIMIENTOS!B:B,"Entrada") -> 0 | C5: =SUMIFS(MOVIMIENTOS!F:F,MOVIMIENTOS!C:C,"Corponor",MOVIMIENTOS!B:B,"Gasto") -> 0 | D5: =B5-C5 -> 0 | E5: =IF(B5=0,0,D5/B5) -> 0 | F5: =IF(B5=0,0,C5/B5) -> 0
A6: Sacyr | B6: =SUMIFS(MOVIMIENTOS!F:F,MOVIMIENTOS!C:C,"Sacyr",MOVIMIENTOS!B:B,"Entrada") -> 0 | C6: =SUMIFS(MOVIMIENTOS!F:F,MOVIMIENTOS!C:C,"Sacyr",MOVIMIENTOS!B:B,"Gasto") -> 0 | D6: =B6-C6 -> 0 | E6: =IF(B6=0,0,D6/B6) -> 0 | F6: =IF(B6=0,0,C6/B6) -> 0
A7: San Roque | B7: =SUMIFS(MOVIMIENTOS!F:F,MOVIMIENTOS!C:C,"San Roque",MOVIMIENTOS!B:B,"Entrada") -> 0 | C7: =SUMIFS(MOVIMIENTOS!F:F,MOVIMIENTOS!C:C,"San Roque",MOVIMIENTOS!B:B,"Gasto") -> 0 | D7: =B7-C7 -> 0 | E7: =IF(B7=0,0,D7/B7) -> 0 | F7: =IF(B7=0,0,C7/B7) -> 0
A8: Consultoria | B8: =SUMIFS(MOVIMIENTOS!F:F,MOVIMIENTOS!C:C,"Consultoria",MOVIMIENTOS!B:B,"Entrada") -> 0 | C8: =SUMIFS(MOVIMIENTOS!F:F,MOVIMIENTOS!C:C,"Consultoria",MOVIMIENTOS!B:B,"Gasto") -> 0 | D8: =B8-C8 -> 0 | E8: =IF(B8=0,0,D8/B8) -> 0 | F8: =IF(B8=0,0,C8/B8) -> 0

Sheet YOGURT
A1: NEGOCIO YOGURT
A4: Cliente | B4: Ingresos | C4: Costos | D4: Utilidad | E4: Litros | F4: Margen | G4: Mejor Cliente
A5: Camilo | B5: =SUMIFS(MOVIMIENTOS!F:F,MOVIMIENTOS!C:C,"Yogurt",MOVIMIENTOS!B:B,"Entrada",MOVIMIENTOS!E:E,"*Camilo*") -> 0 | C5: =SUMIFS(MOVIMIENTOS!F:F,MOVIMIENTOS!C:C,"Yogurt",MOVIMIENTOS!B:B,"Gasto") -> 0 | D5: =B5-C5 -> 0 | E5: =4.5 -> 0 | F5: =IF(B5=0,0,D5/B5) -> 0
A6: Gold Gym | B6: =SUMIFS(MOVIMIENTOS!F:F,MOVIMIENTOS!C:C,"Yogurt",MOVIMIENTOS!B:B,"Entrada",MOVIMIENTOS!E:E,"*Gold Gym*") -> 0 | C6: =SUMIFS(MOVIMIENTOS!F:F,MOVIMIENTOS!C:C,"Yogurt",MOVIMIENTOS!B:B,"Gasto") -> 0 | D6: =B6-C6 -> 0 | E6: =4.5 -> 0 | F6: =IF(B6=0,0,D6/B6) -> 0
A7: Carlos | B7: =SUMIFS(MOVIMIENTOS!F:F,MOVIMIENTOS!C:C,"Yogurt",MOVIMIENTOS!B:B,"Entrada",MOVIMIENTOS!E:E,"*Carlos*") -> 0 | C7: =SUMIFS(MOVIMIENTOS!F:F,MOVIMIENTOS!C:C,"Yogurt",MOVIMIENTOS!B:B,"Gasto") -> 0 | D7: =B7-C7 -> 0 | E7: =4.5 -> 0 | F7: =IF(B7=0,0,D7/B7) -> 0
A8: Mercedes | B8: =SUMIFS(MOVIMIENTOS!F:F,MOVIMIENTOS!C:C,"Yogurt",MOVIMIENTOS!B:B,"Entrada",MOVIMIENTOS!E:E,"*Mercedes*") -> 0 | C8: =SUMIFS(MOVIMIENTOS!F:F,MOVIMIENTOS!C:C,"Yogurt",MOVIMIENTOS!B:B,"Gasto") -> 0 | D8: =B8-C8 -> 0 | E8: =4.5 -> 0 | F8: =IF(B8=0,0,D8/B8) -> 0
A9: Victor | B9: =SUMIFS(MOVIMIENTOS!F:F,MOVIMIENTOS!C:C,"Yogurt",MOVIMIENTOS!B:B,"Entrada",MOVIMIENTOS!E:E,"*Victor*") -> 0 | C9: =SUMIFS(MOVIMIENTOS!F:F,MOVIMIENTOS!C:C,"Yogurt",MOVIMIENTOS!B:B,"Gasto") -> 0 | D9: =B9-C9 -> 0 | E9: =4.5 -> 0 | F9: =IF(B9=0,0,D9/B9) -> 0

Sheet PRESUPUESTO
A1: PRESUPUESTO KAKEIBO
A4: Categoria | B4: Presupuesto | C4: Gasto Real | D4: Disponible | E4: % Usado
A5: Supervivencia | B5: 1200000 | C5: =SUMIFS(MOVIMIENTOS!F:F,MOVIMIENTOS!D:D,"Supervivencia",MOVIMIENTOS!B:B,"Gasto") -> 0 | D5: =B5-C5 -> 0 | E5: =IF(B5=0,0,C5/B5) -> 0
A6: Operacion | B6: 800000 | C6: =SUMIFS(MOVIMIENTOS!F:F,MOVIMIENTOS!D:D,"Operacion",MOVIMIENTOS!B:B,"Gasto") -> 0 | D6: =B6-C6 -> 0 | E6: =IF(B6=0,0,C6/B6) -> 0
A7: Crecimiento | B7: 500000 | C7: =SUMIFS(MOVIMIENTOS!F:F,MOVIMIENTOS!D:D,"Crecimiento",MOVIMIENTOS!B:B,"Gasto") -> 0 | D7: =B7-C7 -> 0 | E7: =IF(B7=0,0,C7/B7) -> 0
A8: Bienestar | B8: 300000 | C8: =SUMIFS(MOVIMIENTOS!F:F,MOVIMIENTOS!D:D,"Bienestar",MOVIMIENTOS!B:B,"Gasto") -> 0 | D8: =B8-C8 -> 0 | E8: =IF(B8=0,0,C8/B8) -> 0
